odoo/addons/ssi_pricelist_mixin/README.rst
odoo/addons/ssi_pricelist_mixin/__init__.py
odoo/addons/ssi_pricelist_mixin/__manifest__.py
odoo/addons/ssi_pricelist_mixin/models/__init__.py
odoo/addons/ssi_pricelist_mixin/models/mixin_pricelist.py
odoo/addons/ssi_pricelist_mixin/static/description/icon.png
odoo14_addon_ssi_pricelist_mixin-14.0.1.1.0.dist-info/METADATA
odoo14_addon_ssi_pricelist_mixin-14.0.1.1.0.dist-info/WHEEL
odoo14_addon_ssi_pricelist_mixin-14.0.1.1.0.dist-info/top_level.txt
odoo14_addon_ssi_pricelist_mixin-14.0.1.1.0.dist-info/RECORD
